Workbook
Name Rule_ID_List: #REF!
Name Group_List: Groups!$A$2:$A$500
Name Bundle_List: 'Permission Bundles'!$A$2:$A$100
Name Rule_ID_List: 'Base Grant Rules'!$A$2:$A$972
Name Data_Product_List: 'Data Products'!$A$2:$A$100
Name Department_List: Departments!$B$2:$B$200
Name LBU_List: LBUs!$B$2:$B$100

Sheet LBUs
A1: full_name | B1: lbu_abbreviation | C1: description
A2: All Approved LBUs | B2: all | C2: Cross-LBU scope covering all approved LBUs
A3: Singapore | B3: sg | C3: Local business unit
A4: Hong Kong | B4: hk | C4: Local business unit
A5: Malaysia | B5: my | C5: Local business unit
A6: Taiwan | B6: tw | C6: Local business unit
A7: Indonesia | B7: id | C7: Local business unit
A8: Vietnam | B8: vn | C8: Local business unit
A9: China | B9: cn | C9: Local business unit
A10: Japan | B10: jp | C10: Local business unit

Sheet Departments
A1: full_name | B1: department_id
A2: Performance & Attribution | B2: pna
A3: Investment Risk | B3: investment-risk
A4: Compliance | B4: compliance
A5: ESG | B5: esg
A6: Data Operations | B6: data-operations
A7: Marketing and Distribution | B7: marketing-distribution
A8: Client and Fund Reporting | B8: cfr
A9: Middle Office Operations | B9: middle-office-operations
A10: Front Office Operations | B10: front-office-operations
A11: Human Resources | B11: hr
A12: Transformation (Project Management Office) | B12: transformation-pmo
... A21: ADMIN | B21: admin

Sheet Permission Bundles
A1: bundle | B1: purpose | C1: privilege_summary
A2: READ | B2: Query explicitly approved existing data | C2: USE CATALOG USE SCHEMA SELECT on selected tables, views, materialized views, or streaming tables EXECUTE on selected functions READ VOLUME on selected volumes
A3: WRITE | B3: Read and mutate data in approved existing tables | C3: USE CATALOG USE SCHEMA SELECT on selected tables MODIFY on selected tables
A4: OWNER | B4: Create application objects in an approved pre-provisioned schema | C4: USE CATALOG USE SCHEMA CREATE TABLE CREATE FUNCTION CREATE VOLUME CREATE MATERIALIZED VIEW
A5: ADMIN | B5: Administer privileges and ownership in an approved UC scope | C5: USE CATALOG or USE SCHEMA as required MANAGE on the selected catalog, schema, or object

Sheet Groups
A1: group_name | B1: lbu_abbreviation | C1: department_id | D1: bundle | E1: mask_treatment
A2: =IF(OR(B2="",C2="",D2="",E2=""),"","GSGEIS-hera-"&LOWER(SUBSTITUTE(TRIM(B2)," ","-"))&"-"&LOWER(SUBSTITUTE(TRIM(C2)," ","-"))&"-"&LOWER(SUBSTITUTE(TRIM(D2)," ","-"))&"-"&LOWER(SUBSTITUTE(TRIM(E2)," ","-"))) -> GSGEIS-hera-all-esg-read-unmasked | B2: all | C2: esg | D2: READ | E2: unmasked
A3: =IF(OR(B3="",C3="",D3="",E3=""),"","GSGEIS-hera-"&LOWER(SUBSTITUTE(TRIM(B3)," ","-"))&"-"&LOWER(SUBSTITUTE(TRIM(C3)," ","-"))&"-"&LOWER(SUBSTITUTE(TRIM(D3)," ","-"))&"-"&LOWER(SUBSTITUTE(TRIM(E3)," ","-"))) -> GSGEIS-hera-all-esg-read-masked | B3: all | C3: esg | D3: READ | E3: masked
A4: =IF(OR(B4="",C4="",D4="",E4=""),"","GSGEIS-hera-"&LOWER(SUBSTITUTE(TRIM(B4)," ","-"))&"-"&LOWER(SUBSTITUTE(TRIM(C4)," ","-"))&"-"&LOWER(SUBSTITUTE(TRIM(D4)," ","-"))&"-"&LOWER(SUBSTITUTE(TRIM(E4)," ","-"))) -> GSGEIS-hera-sg-esg-read-masked | B4: sg | C4: esg | D4: READ | E4: masked
A5: =IF(OR(B5="",C5="",D5="",E5=""),"","GSGEIS-hera-"&LOWER(SUBSTITUTE(TRIM(B5)," ","-"))&"-"&LOWER(SUBSTITUTE(TRIM(C5)," ","-"))&"-"&LOWER(SUBSTITUTE(TRIM(D5)," ","-"))&"-"&LOWER(SUBSTITUTE(TRIM(E5)," ","-"))) -> GSGEIS-hera-sg-eq-read-masked | B5: sg | C5: eq | D5: READ | E5: masked
A6: =IF(OR(B6="",C6="",D6="",E6=""),"","GSGEIS-hera-"&LOWER(SUBSTITUTE(TRIM(B6)," ","-"))&"-"&LOWER(SUBSTITUTE(TRIM(C6)," ","-"))&"-"&LOWER(SUBSTITUTE(TRIM(D6)," ","-"))&"-"&LOWER(SUBSTITUTE(TRIM(E6)," ","-"))) -> GSGEIS-hera-sg-fi-read-masked | B6: sg | C6: fi | D6: READ | E6: masked
A7: =IF(OR(B7="",C7="",D7="",E7=""),"","GSGEIS-hera-"&LOWER(SUBSTITUTE(TRIM(B7)," ","-"))&"-"&LOWER(SUBSTITUTE(TRIM(C7)," ","-"))&"-"&LOWER(SUBSTITUTE(TRIM(D7)," ","-"))&"-"&LOWER(SUBSTITUTE(TRIM(E7)," ","-"))) -> GSGEIS-hera-all-admin-admin-unmasked | B7: all | C7: admin | D7: ADMIN | E7: unmasked
A8: =IF(OR(B8="",C8="",D8="",E8=""),"","hera-"&LOWER(SUBSTITUTE(TRIM(B8)," ","-"))&"-"&LOWER(SUBSTITUTE(TRIM(C8)," ","-"))&"-"&LOWER(SUBSTITUTE(TRIM(D8)," ","-"))&"-"&LOWER(SUBSTITUTE(TRIM(E8)," ","-")))
A9: =IF(OR(B9="",C9="",D9="",E9=""),"","hera-"&LOWER(SUBSTITUTE(TRIM(B9)," ","-"))&"-"&LOWER(SUBSTITUTE(TRIM(C9)," ","-"))&"-"&LOWER(SUBSTITUTE(TRIM(D9)," ","-"))&"-"&LOWER(SUBSTITUTE(TRIM(E9)," ","-")))
A10: =IF(OR(B10="",C10="",D10="",E10=""),"","hera-"&LOWER(SUBSTITUTE(TRIM(B10)," ","-"))&"-"&LOWER(SUBSTITUTE(TRIM(C10)," ","-"))&"-"&LOWER(SUBSTITUTE(TRIM(D10)," ","-"))&"-"&LOWER(SUBSTITUTE(TRIM(E10)," ","-")))
A11: =IF(OR(B11="",C11="",D11="",E11=""),"","hera-"&LOWER(SUBSTITUTE(TRIM(B11)," ","-"))&"-"&LOWER(SUBSTITUTE(TRIM(C11)," ","-"))&"-"&LOWER(SUBSTITUTE(TRIM(D11)," ","-"))&"-"&LOWER(SUBSTITUTE(TRIM(E11)," ","-")))
A12: =IF(OR(B12="",C12="",D12="",E12=""),"","hera-"&LOWER(SUBSTITUTE(TRIM(B12)," ","-"))&"-"&LOWER(SUBSTITUTE(TRIM(C12)," ","-"))&"-"&LOWER(SUBSTITUTE(TRIM(D12)," ","-"))&"-"&LOWER(SUBSTITUTE(TRIM(E12)," ","-")))
A13: =IF(OR(B13="",C13="",D13="",E13=""),"","hera-"&LOWER(SUBSTITUTE(TRIM(B13)," ","-"))&"-"&LOWER(SUBSTITUTE(TRIM(C13)," ","-"))&"-"&LOWER(SUBSTITUTE(TRIM(D13)," ","-"))&"-"&LOWER(SUBSTITUTE(TRIM(E13)," ","-")))
A14: =IF(OR(B14="",C14="",D14="",E14=""),"","hera-"&LOWER(SUBSTITUTE(TRIM(B14)," ","-"))&"-"&LOWER(SUBSTITUTE(TRIM(C14)," ","-"))&"-"&LOWER(SUBSTITUTE(TRIM(D14)," ","-"))&"-"&LOWER(SUBSTITUTE(TRIM(E14)," ","-")))
A15: =IF(OR(B15="",C15="",D15="",E15=""),"","hera-"&LOWER(SUBSTITUTE(TRIM(B15)," ","-"))&"-"&LOWER(SUBSTITUTE(TRIM(C15)," ","-"))&"-"&LOWER(SUBSTITUTE(TRIM(D15)," ","-"))&"-"&LOWER(SUBSTITUTE(TRIM(E15)," ","-")))
A16: =IF(OR(B16="",C16="",D16="",E16=""),"","hera-"&LOWER(SUBSTITUTE(TRIM(B16)," ","-"))&"-"&LOWER(SUBSTITUTE(TRIM(C16)," ","-"))&"-"&LOWER(SUBSTITUTE(TRIM(D16)," ","-"))&"-"&LOWER(SUBSTITUTE(TRIM(E16)," ","-")))
A17: =IF(OR(B17="",C17="",D17="",E17=""),"","hera-"&LOWER(SUBSTITUTE(TRIM(B17)," ","-"))&"-"&LOWER(SUBSTITUTE(TRIM(C17)," ","-"))&"-"&LOWER(SUBSTITUTE(TRIM(D17)," ","-"))&"-"&LOWER(SUBSTITUTE(TRIM(E17)," ","-")))
A18: =IF(OR(B18="",C18="",D18="",E18=""),"","hera-"&LOWER(SUBSTITUTE(TRIM(B18)," ","-"))&"-"&LOWER(SUBSTITUTE(TRIM(C18)," ","-"))&"-"&LOWER(SUBSTITUTE(TRIM(D18)," ","-"))&"-"&LOWER(SUBSTITUTE(TRIM(E18)," ","-")))
A19: =IF(OR(B19="",C19="",D19="",E19=""),"","hera-"&LOWER(SUBSTITUTE(TRIM(B19)," ","-"))&"-"&LOWER(SUBSTITUTE(TRIM(C19)," ","-"))&"-"&LOWER(SUBSTITUTE(TRIM(D19)," ","-"))&"-"&LOWER(SUBSTITUTE(TRIM(E19)," ","-")))
... A500: =IF(OR(B500="",C500="",D500="",E500=""),"","hera-"&LOWER(SUBSTITUTE(TRIM(B500)," ","-"))&"-"&LOWER(SUBSTITUTE(TRIM(C500)," ","-"))&"-"&LOWER(SUBSTITUTE(TRIM(D500)," ","-"))&"-"&LOWER(SUBSTITUTE(TRIM(E500)," ","-")))

Sheet Data Products
A1: data_product | B1: description
A2: investment_esg | B2: ESG related data
A3: portfolio_position | B3: Portfolio position data
A4: portfolio_transaction | B4: Portfolio transaction data
A5: investment_research | B5: Investment research data
A6: mdm_portfolio_structure | B6: Master reference data for portfolios, funds, mandates, and share classes
A7: mdm_security | B7: Master security reference data
A8: market_data | B8: Market data such as security prices

Sheet Base Tables
A1: catalog | B1: schema | C1: object | D1: object_type | E1: data_product | F1: target_schema | G1: rls_column
A2: hera-dev | B2: gold | C2: esg_engagement | D2: table | E2: investment_research | F2: hera-dev.dm_esg
A3: hera-dev | B3: gold | C3: esg_waci | D3: table | E3: investment_esg | F3: hera-dev.dm_esg
A4: hera-dev | B4: silver | C4: fact_esg_engagement | D4: table | E4: investment_research | F4: hera-dev.dm_esg
A5: hera-dev | B5: silver | C5: fact_portfolio_position | D5: table | E5: portfolio_position | F5: hera-dev.dm_esg | G5: portfolio_code
A6: hera-dev | B6: silver | C6: dim_portfolio | D6: table | E6: mdm_portfolio_structure | F6: hera-dev.dm_esg | G6: portfolio_code
A7: hera-dev | B7: silver | C7: dim_fund | D7: table | E7: mdm_portfolio_structure | F7: hera-dev.dm_esg
A8: hera-dev | B8: silver | C8: dim_mandate | D8: table | E8: mdm_portfolio_structure | F8: hera-dev.dm_esg
A9: hera-dev | B9: silver | C9: dim_share_class | D9: table | E9: mdm_portfolio_structure | F9: hera-dev.dm_esg
A10: hera-dev | B10: silver | C10: fact_portfolio_transaction | D10: table | E10: portfolio_transaction | F10: hera-dev.dm_esg | G10: portfolio_code
A11: hera-dev | B11: silver | C11: fact_price | D11: table | E11: market_data | F11: hera-dev.dm_esg
A12: hera-dev | B12: silver | C12: fact_portfolio_position | D12: table | E12: portfolio_position | F12: hera-dev.dm_something | G12: portfolio_code

Sheet Base Grant Rules
A1: rule_id | B1: group_name | C1: match_label_key | D1: match_label_value | E1: bundle | F1: object_types
A2: GR001 | B2: GSGEIS-hera-all-admin-admin-unmasked | C2: data_product | D2: investment_esg | E2: {=IF(B2="","",IFERROR(INDEX(Groups!$D$2:$D$500,MATCH(B2,Groups!$A$2:$A$500,0)),""))} -> ADMIN | F2: table; view
A3: GR002 | B3: GSGEIS-hera-all-admin-admin-unmasked | C3: data_product | D3: portfolio_position | E3: {=IF(B3="","",IFERROR(INDEX(Groups!$D$2:$D$500,MATCH(B3,Groups!$A$2:$A$500,0)),""))} -> ADMIN | F3: table; view
A4: GR003 | B4: GSGEIS-hera-all-admin-admin-unmasked | C4: data_product | D4: portfolio_transaction | E4: {=IF(B4="","",IFERROR(INDEX(Groups!$D$2:$D$500,MATCH(B4,Groups!$A$2:$A$500,0)),""))} -> ADMIN | F4: table; view
A5: GR004 | B5: GSGEIS-hera-all-admin-admin-unmasked | C5: data_product | D5: investment_research | E5: {=IF(B5="","",IFERROR(INDEX(Groups!$D$2:$D$500,MATCH(B5,Groups!$A$2:$A$500,0)),""))} -> ADMIN | F5: table; view
A6: GR005 | B6: GSGEIS-hera-all-admin-admin-unmasked | C6: data_product | D6: mdm_portfolio_structure | E6: {=IF(B6="","",IFERROR(INDEX(Groups!$D$2:$D$500,MATCH(B6,Groups!$A$2:$A$500,0)),""))} -> ADMIN | F6: table; view
A7: GR006 | B7: GSGEIS-hera-all-admin-admin-unmasked | C7: data_product | D7: mdm_security | E7: {=IF(B7="","",IFERROR(INDEX(Groups!$D$2:$D$500,MATCH(B7,Groups!$A$2:$A$500,0)),""))} -> ADMIN | F7: table; view
A8: GR007 | B8: GSGEIS-hera-all-admin-admin-unmasked | C8: data_product | D8: market_data | E8: {=IF(B8="","",IFERROR(INDEX(Groups!$D$2:$D$500,MATCH(B8,Groups!$A$2:$A$500,0)),""))} -> ADMIN | F8: table; view
E9: {=IF(B9="","",IFERROR(INDEX(Groups!$D$2:$D$500,MATCH(B9,Groups!$A$2:$A$500,0)),""))}
E10: {=IF(B10="","",IFERROR(INDEX(Groups!$D$2:$D$500,MATCH(B10,Groups!$A$2:$A$500,0)),""))}
E11: {=IF(B11="","",IFERROR(INDEX(Groups!$D$2:$D$500,MATCH(B11,Groups!$A$2:$A$500,0)),""))}
E12: {=IF(B12="","",IFERROR(INDEX(Groups!$D$2:$D$500,MATCH(B12,Groups!$A$2:$A$500,0)),""))}
E13: {=IF(B13="","",IFERROR(INDEX(Groups!$D$2:$D$500,MATCH(B13,Groups!$A$2:$A$500,0)),""))}
E14: {=IF(B14="","",IFERROR(INDEX(Groups!$D$2:$D$500,MATCH(B14,Groups!$A$2:$A$500,0)),""))}
E15: {=IF(B15="","",IFERROR(INDEX(Groups!$D$2:$D$500,MATCH(B15,Groups!$A$2:$A$500,0)),""))}
E16: {=IF(B16="","",IFERROR(INDEX(Groups!$D$2:$D$500,MATCH(B16,Groups!$A$2:$A$500,0)),""))}
E17: {=IF(B17="","",IFERROR(INDEX(Groups!$D$2:$D$500,MATCH(B17,Groups!$A$2:$A$500,0)),""))}
E18: {=IF(B18="","",IFERROR(INDEX(Groups!$D$2:$D$500,MATCH(B18,Groups!$A$2:$A$500,0)),""))}
E19: {=IF(B19="","",IFERROR(INDEX(Groups!$D$2:$D$500,MATCH(B19,Groups!$A$2:$A$500,0)),""))}
E20: {=IF(B20="","",IFERROR(INDEX(Groups!$D$2:$D$500,MATCH(B20,Groups!$A$2:$A$500,0)),""))}
... E972: {=IF(B972="","",IFERROR(INDEX(Groups!$D$2:$D$500,MATCH(B972,Groups!$A$2:$A$500,0)),""))}

Sheet Base Grant Exceptions
A1: exception_id | B1: rule_id | C1: action | D1: object_type | E1: object
A2: EX001 | B2: GR001 | C2: include | D2: table | E2: hera-dev.governance.example_esg_helper
A3: EX002 | B3: GR001 | C3: exclude | D3: table | E3: hera-dev.gold.example_restricted_esg

Sheet Rbac Views
A1: rule_id | B1: group_name | C1: catalog | D1: schema | E1: bundle
A2: RBAC001 | B2: GSGEIS-hera-all-esg-read-masked | C2: hera-dev | D2: dm_esg | E2: READ
A3: RBAC002 | B3: GSGEIS-hera-all-esg-read-unmasked | C3: hera-dev | D3: dm_esg | E3: READ
A4: RBAC003 | B4: GSGEIS-hera-sg-eq-read-masked | C4: hera-dev | D4: dm_esg | E4: READ
A5: RBAC004 | B5: GSGEIS-hera-sg-esg-read-masked | C5: hera-dev | D5: dm_esg | E5: READ
A6: RBAC005 | B6: GSGEIS-hera-sg-fi-read-masked | C6: hera-dev | D6: dm_esg | E6: READ

Sheet Asset Classification
A1: object | B1: tag_key | C1: tag_value
A2: hera-dev.gold.esg_engagement.author | B2: acm_pii_type | C2: FULL_NAME
A3: hera-dev.silver.fact_esg_engagement.author | B3: acm_pii_type | C3: FULL_NAME
A4: hera-dev.silver.fact_portfolio_position.portfolio_code | B4: acm_pii_type | C4: identifier
A5: hera-dev.silver.dim_portfolio.portfolio_code | B5: acm_pii_type | C5: identifier
A6: hera-dev.silver.dim_fund.portfolio_code | B6: acm_pii_type | C6: identifier
A7: hera-dev.silver.dim_mandate.portfolio_code | B7: acm_pii_type | C7: identifier
A8: hera-dev.gold.esg_waci.portfolio_code | B8: acm_pii_type | C8: identifier

Sheet Masking Rules
A1: attach | B1: when_key | C1: when_value | D1: match_columns_key | E1: match_columns_value | F1: function
A2: hera-dev.gold | B2: data_product | C2: investment_research | D2: acm_pii_type | E2: FULL_NAME | F2: hera-dev.governance.acm_mask_full_name
A3: hera-dev.gold | B3: data_product | C3: investment_research | D3: acm_pii_type | E3: EMAIL | F3: hera-dev.governance.acm_mask_email
A4: hera-dev.gold | B4: data_product | C4: investment_research | D4: acm_pii_type | E4: PASSPORT | F4: hera-dev.governance.acm_mask_passport
A5: hera-dev.silver | B5: data_product | C5: portfolio_position | D5: acm_pii_type | E5: identifier | F5: hera-dev.governance.acm_mask_identifier

Sheet RLS Rules (Deprecated)
A1: attach | B1: when_key | C1: when_value | D1: match_columns_key | E1: match_columns_value | F1: function
A2: hera-dev.silver.fact_portfolio_position | D2: rls | E2: portfolio_scope | F2: hera-dev.silver.portfolio_scope_filter
A3: hera-dev.silver.dim_portfolio | D3: rls | E3: portfolio_scope | F3: hera-dev.silver.portfolio_scope_filter
A4: hera-dev.silver.dim_fund | D4: rls | E4: portfolio_scope | F4: hera-dev.silver.portfolio_scope_filter
A5: hera-dev.silver.dim_mandate | D5: rls | E5: portfolio_scope | F5: hera-dev.silver.portfolio_scope_filter
A6: hera-dev.gold.esg_waci | D6: rls | E6: portfolio_scope | F6: hera-dev.silver.portfolio_scope_filter

Sheet RLS Entitlements (Move to delta
A1: ad_group | B1: tag | C1: type | D1: value
A2: GSGEIS-hera-all-esg-read-masked | B2: portfolio_scope | C2: region | D2: *
A3: GSGEIS-hera-all-esg-read-masked | B3: portfolio_scope | C3: team | D3: *
A4: GSGEIS-hera-all-esg-read-unmasked | B4: portfolio_scope | C4: region | D4: *
A5: GSGEIS-hera-all-esg-read-unmasked | B5: portfolio_scope | C5: team | D5: *
A6: GSGEIS-hera-sg-eq-read-masked | B6: portfolio_scope | C6: region | D6: EISG
A7: GSGEIS-hera-sg-eq-read-masked | B7: portfolio_scope | C7: team | D7: EQ
A8: GSGEIS-hera-sg-esg-read-masked | B8: portfolio_scope | C8: region | D8: EISG
A9: GSGEIS-hera-sg-esg-read-masked | B9: portfolio_scope | C9: team | D9: *
A10: GSGEIS-hera-sg-fi-read-masked | B10: portfolio_scope | C10: region | D10: EISG
A11: GSGEIS-hera-sg-fi-read-masked | B11: portfolio_scope | C11: team | D11: FI

Sheet RLS Entitlement Mapping (Move t
A1: type | B1: value | C1: portfolio_code
A2: region | B2: AGFINV | C2: IOFGGE
A3: region | B3: ALPINVUS | C3: BHBHPE
A4: region | B4: AMUNDIAM | C4: BALANC
A5: region | B5: AMUNDIAM | C5: ESUGA1
A6: region | B6: AMUNDIAM | C6: ESUGA2
A7: region | B7: AMUNDIAM | C7: ESUGA3
A8: region | B8: AMUNDIAM | C8: EXPLOR
A9: region | B9: AMUNDIAM | C9: NURTUR
A10: region | B10: BRFM | C10: BHBLIG
A11: region | B11: BRFM | C11: BSBRIG
A12: region | B12: CAMIL | C12: BSEAGE
... A2953: team | B2953: QS | C2953: NDPDGT

Sheet Workspace Objects
A1: object_type | B1: object | C1: group_name | D1: permission_level | E1: environment | F1: reason
